<?xml version="1.0" encoding="UTF-8"?>
<config xmlns:xsi="http://www.w3.org/2001/XMLSchema-instance" xmlns="http://www.oxygenxml.com/ns/ccfilter/simple"
        xsi:noNamespaceSchemaLocation="configurationCC.xsd">
    <!--<match elementName="prodname">
        <items>
            <item value="Car"/>
            <item value="Bus"/>
        </items>
    </match>
    
    <match elementName="writing" elementNS="http://www.tei-c.org/ns/1.0" attrName="who">
        <xslt href="../xsl/get_values_from_db.xsl" useCache="false"  action="replace"/>
    </match>-->

    <match attrName="hand">
        <xslt href="../hand.xsl" useCache="false" action="replace"/>
    </match>

    <match elementName="handShift" elementNS="http://www.tei-c.org/ns/1.0" attrName="new">
        <xslt href="../hand.xsl" useCache="false" action="replace"/>
    </match>
</config>
